namecast/__init__.py
namecast/api.py
namecast/cli.py
namecast/evaluator.py
namecast/perception.py
namecast/phonetic.py
namecast/tests/__init__.py
namecast/tests/test_evaluator.py
namecast-0.1.0.dist-info/METADATA
namecast-0.1.0.dist-info/WHEEL
namecast-0.1.0.dist-info/entry_points.txt
namecast-0.1.0.dist-info/top_level.txt
namecast-0.1.0.dist-info/RECORD
