Metadata-Version: 2.4
Name: namecast
Version: 0.1.0
Summary: AI-powered brand name oracle - forecast your name's future
Author: Max Ghenis
License: MIT
Classifier: Development Status :: 3 - Alpha
Classifier: Intended Audience :: Developers
Classifier: License :: OSI Approved :: MIT License
Classifier: Programming Language :: Python :: 3
Classifier: Programming Language :: Python :: 3.10
Classifier: Programming Language :: Python :: 3.11
Classifier: Programming Language :: Python :: 3.12
Requires-Python: >=3.10
Requires-Dist: click>=8.0
Requires-Dist: httpx>=0.25
Requires-Dist: python-whois>=0.8
Requires-Dist: anthropic>=0.18
Requires-Dist: rich>=13.0
Requires-Dist: fastapi>=0.109
Requires-Dist: uvicorn>=0.27
Provides-Extra: phonetic
Requires-Dist: big-phoney>=1.0; extra == "phonetic"
Provides-Extra: dev
Requires-Dist: pytest>=7.0; extra == "dev"
Requires-Dist: pytest-asyncio>=0.21; extra == "dev"
Requires-Dist: pytest-mock>=3.0; extra == "dev"
